RTL_Anas/DQPSK_DUT/RTL/DQPSK.V
module DQPSK (
    input  wire              clk, rst_n, i_valid,
    input  wire signed [1:0] Real, Imag,
    output reg               o_valid,
    output reg  signed [1:0] Real_o, Imag_o
);

reg signed [1:0] Real_FF [0:3];
reg signed [1:0] Imag_FF [0:3]; 

always @(posedge clk) begin
    if (!rst_n) begin
        Real_FF[0] <= 2'sb01; Real_FF[1] <= 2'sb01; Real_FF[2] <= 2'sb01; Real_FF[3] <= 2'sb01;
        Imag_FF[0] <= 2'sb01; Imag_FF[1] <= 2'sb01; Imag_FF[2] <= 2'sb01; Imag_FF[3] <= 2'sb01;
        Real_o  <= 2'sb00;
        Imag_o  <= 2'sb00;
        o_valid <= 1'b0;
    end
    else begin
        o_valid <= i_valid;
        if (i_valid) begin
            // Register calculated output to align with registered o_valid
            Real_o <= (Real * Real_FF[3]) - (Imag * Imag_FF[3]);
            Imag_o <= (Real * Imag_FF[3]) + (Imag * Real_FF[3]);

            // Shift delay chain using calculated result
            {Real_FF[3], Real_FF[2], Real_FF[1], Real_FF[0]} <= {Real_FF[2], Real_FF[1], Real_FF[0], (Real * Real_FF[3]) - (Imag * Imag_FF[3])}; 
            {Imag_FF[3], Imag_FF[2], Imag_FF[1], Imag_FF[0]} <= {Imag_FF[2], Imag_FF[1], Imag_FF[0], (Real * Imag_FF[3]) + (Imag * Real_FF[3])};  
        end
    end
end

endmodule

RTL_Anas/DQPSK_DUT/TB/DQPSK_TB.SV
`timescale 1ns/1ps

module tb_DQPSK;

    // Testbench Signals
    reg              clk;
    reg              rst_n;
    reg              i_valid;
    reg  signed [1:0] Real, Imag;

    wire             o_valid;
    wire signed [1:0] Real_o, Imag_o;

    // Statistics & Verification Counters
    integer pass_count = 0;
    integer fail_count = 0;
    integer symbol_counter = 0;

    // Golden Reference Model State Registers
    reg signed [1:0] ref_R [0:3];
    reg signed [1:0] ref_I [0:3];
    reg signed [1:0] exp_R_q;
    reg signed [1:0] exp_I_q;
    reg              exp_valid_q;

    // QPSK Symbol Constants
    localparam signed [1:0] P_ONE  = 2'sb01; //  1
    localparam signed [1:0] N_ONE  = 2'sb11; // -1
    localparam signed [1:0] ZERO   = 2'sb00; //  0

    // Instantiate Design Under Test (DUT)
    DQPSK dut (
        .clk(clk),
        .rst_n(rst_n),
        .i_valid(i_valid),
        .Real(Real),
        .Imag(Imag),
        .o_valid(o_valid),
        .Real_o(Real_o),
        .Imag_o(Imag_o)
    );

    // 100 MHz Clock Generation (10 ns period)
    always #5 clk = ~clk;

    // =========================================================================
    // GOLDEN REFERENCE MODEL (1-cycle latency pipeline)
    // =========================================================================
    always @(posedge clk or negedge rst_n) begin
        if (!rst_n) begin
            ref_R[0] <= 2'sb01; ref_R[1] <= 2'sb01; ref_R[2] <= 2'sb01; ref_R[3] <= 2'sb01;
            ref_I[0] <= 2'sb01; ref_I[1] <= 2'sb01; ref_I[2] <= 2'sb01; ref_I[3] <= 2'sb01;
            exp_R_q     <= 2'sb00;
            exp_I_q     <= 2'sb00;
            exp_valid_q <= 1'b0;
        end else begin
            exp_valid_q <= i_valid;
            if (i_valid) begin
                // Predict registered output
                exp_R_q <= (Real * ref_R[3]) - (Imag * ref_I[3]);
                exp_I_q <= (Real * ref_I[3]) + (Imag * ref_R[3]);

                // Update internal reference feedback delay line
                {ref_R[3], ref_R[2], ref_R[1], ref_R[0]} <= {ref_R[2], ref_R[1], ref_R[0], (Real * ref_R[3]) - (Imag * ref_I[3])};
                {ref_I[3], ref_I[2], ref_I[1], ref_I[0]} <= {ref_I[2], ref_I[1], ref_I[0], (Real * ref_I[3]) + (Imag * ref_R[3])};
            end
        end
    end

    // =========================================================================
    // AUTOMATED CHECKER (Evaluated on falling clock edge to prevent race condition)
    // =========================================================================
    always @(negedge clk) begin
        if (rst_n) begin
            // Check valid flag alignment
            if (o_valid !== exp_valid_q) begin
                $display("[ERROR @ %0tps] Valid Flag Mismatch! Expected: %b, Got: %b", $time, exp_valid_q, o_valid);
                fail_count = fail_count + 1;
            end

            // Check math output when data is valid
            if (o_valid) begin
                symbol_counter = symbol_counter + 1;
                if ((Real_o === exp_R_q) && (Imag_o === exp_I_q)) begin
                    $display("[PASS  @ %0tps] Symbol #%0d | Output: (%2d, %2d)", $time, symbol_counter, Real_o, Imag_o);
                    pass_count = pass_count + 1;
                end else begin
                    $display("[FAIL  @ %0tps] Symbol #%0d | Expected: (%2d, %2d), Got: (%2d, %2d)", 
                              $time, symbol_counter, exp_R_q, exp_I_q, Real_o, Imag_o);
                    fail_count = fail_count + 1;
                end
            end
        end
    end

    // =========================================================================
    // TASKS FOR DRIVING INPUTS
    // =========================================================================
    task send_symbol(input signed [1:0] r_in, input signed [1:0] i_in);
        begin
            @(posedge clk);
            Real    <= r_in;
            Imag    <= i_in;
            i_valid <= 1'b1;
        end
    endtask

    task send_idle(input integer cycles);
        integer k;
        begin
            for (k = 0; k < cycles; k = k + 1) begin
                @(posedge clk);
                Real    <= ZERO;
                Imag    <= ZERO;
                i_valid <= 1'b0;
            end
        end
    endtask

    // =========================================================================
    // STIMULUS SUITE
    // =========================================================================
    initial begin
        $dumpfile("dqpsk_tb.vcd");
        $dumpvars(0, tb_DQPSK);

        // Initialize Inputs
        clk     = 1'b0;
        rst_n   = 1'b0;
        i_valid = 1'b0;
        Real    = ZERO;
        Imag    = ZERO;

        // --- TEST 1: Reset Verification ---
        $display("\n--- TEST 1: Reset Sequence ---");
        #25;
        rst_n = 1'b1;
        send_idle(2);

        // --- TEST 2: Single Isolated Symbols (Gapped Stream) ---
        $display("\n--- TEST 2: Isolated Symbols (+1, +j, -1, -j) ---");
        send_symbol(P_ONE, ZERO);  // +1
        send_idle(3);
        send_symbol(ZERO,  P_ONE); // +j
        send_idle(3);
        send_symbol(N_ONE, ZERO);  // -1
        send_idle(3);
        send_symbol(ZERO,  N_ONE); // -j
        send_idle(4);

        // --- TEST 3: Continuous Stream (Full Differential Buffer Circulation) ---
        $display("\n--- TEST 3: Continuous Symbol Stream (12 Symbols) ---");
        send_symbol(P_ONE, ZERO);  // +1
        send_symbol(ZERO,  P_ONE); // +j
        send_symbol(N_ONE, ZERO);  // -1
        send_symbol(ZERO,  N_ONE); // -j
        send_symbol(P_ONE, ZERO);  // +1
        send_symbol(P_ONE, ZERO);  // +1
        send_symbol(ZERO,  P_ONE); // +j
        send_symbol(N_ONE, ZERO);  // -1
        send_symbol(ZERO,  N_ONE); // -j
        send_symbol(N_ONE, ZERO);  // -1
        send_symbol(ZERO,  P_ONE); // +j
        send_symbol(P_ONE, ZERO);  // +1
        send_idle(5);

        // --- TEST 4: Intermittent Stalled Stream (Random Valid Gating) ---
        $display("\n--- TEST 4: Intermittent Stream (Pause/Resume State Hold) ---");
        send_symbol(P_ONE, ZERO);
        send_symbol(ZERO,  N_ONE);
        send_idle(2);
        send_symbol(N_ONE, ZERO);
        send_idle(1);
        send_symbol(ZERO,  P_ONE);
        send_idle(4);

        // --- FINAL SUMMARY ---
        $display("\n==================================================");
        $display("               SIMULATION RESULTS                 ");
        $display("==================================================");
        $display(" Total Symbols Checked : %0d", symbol_counter);
        $display(" Passed Checks         : %0d", pass_count);
        $display(" Failed Checks         : %0d", fail_count);
        $display("==================================================");

        if (fail_count == 0 && pass_count > 0)
            $display(" STATUS: TEST PASSED SUCCESSFULLY!");
        else
            $display(" STATUS: TEST FAILED WITH ERRORS!");

        $finish;
    end

endmodule

RTL_Anas/DQPSK_DUT/Build/dqpsk_tb.vcd
$date
	Thu Sep  3 00:25:03 2026
$end
$version
	Questa Altera Starter FPGA Edition Version 2025.2
$end
$timescale
	1ps
$end

$scope module tb_DQPSK $end
$var parameter 2 ! P_ONE $end
$var parameter 2 " N_ONE $end
$var parameter 2 # ZERO $end
$var reg 1 $ clk $end
$var reg 1 % rst_n $end
$var reg 1 & i_valid $end
$var reg 2 ' Real [1:0] $end
$var reg 2 ( Imag [1:0] $end
$var wire 1 ) o_valid $end
$var wire 1 * Real_o [1] $end
$var wire 1 + Real_o [0] $end
$var wire 1 , Imag_o [1] $end
$var wire 1 - Imag_o [0] $end
$var integer 32 . pass_count $end
$var integer 32 / fail_count $end
$var integer 32 0 symbol_counter $end
$var reg 2 1 exp_R_q [1:0] $end
$var reg 2 2 exp_I_q [1:0] $end
$var reg 1 3 exp_valid_q $end

$scope task send_symbol $end
$var reg 2 4 r_in [1:0] $end
$var reg 2 5 i_in [1:0] $end
$upscope $end

$scope task send_idle $end
$var integer 32 6 cycles $end
$var integer 32 7 k $end
$upscope $end

$scope module dut $end
$var wire 1 8 clk $end
$var wire 1 9 rst_n $end
$var wire 1 : i_valid $end
$var wire 1 ; Real [1] $end
$var wire 1 < Real [0] $end
$var wire 1 = Imag [1] $end
$var wire 1 > Imag [0] $end
$var reg 1 ? o_valid $end
$var reg 2 @ Real_o [1:0] $end
$var reg 2 A Imag_o [1:0] $end
$upscope $end
$upscope $end
$enddefinitions $end
#0
$dumpvars
0$
0%
0&
b0 '
b0 (
b0 1
b0 2
03
x?
bx @
bx A
bx 4
bx 5
b1 !
b11 "
b0 #
b0 .
b0 /
b0 0
bx 6
bx 7
x)
x+
x*
x-
x,
0>
0=
0<
0;
0:
09
08
$end
#5000
1$
18
b0 @
b0 A
0?
0-
0,
0+
0*
0)
#10000
0$
08
#15000
1$
18
#20000
0$
08
#25000
1%
b10 6
b0 7
1$
19
18
b1 7
#30000
0$
08
#35000
1$
18
b10 7
b1 4
b0 5
#40000
0$
08
#45000
1$
18
b11 6
b0 7
b1 '
1&
1<
1:
#50000
0$
08
#55000
1$
18
b1 7
1?
b1 @
b1 A
13
b1 1
b1 2
b0 '
0&
1)
0<
1-
1+
0:
#60000
0$
08
b1 0
b1 .
#65000
1$
18
b10 7
0?
03
0)
#70000
0$
08
#75000
1$
18
b11 7
b0 4
b1 5
#80000
0$
08
#85000
1$
18
b0 7
b1 (
1&
1>
1:
#90000
0$
08
#95000
1$
18
b1 7
1?
b11 @
13
b11 1
b0 (
0&
1)
0>
1*
0:
#100000
0$
08
b10 0
b10 .
#105000
1$
18
b10 7
0?
03
0)
#110000
0$
08
#115000
1$
18
b11 7
b11 4
b0 5
#120000
0$
08
#125000
1$
18
b0 7
b11 '
1&
1<
1;
1:
#130000
0$
08
#135000
1$
18
b1 7
1?
b11 A
13
b11 2
b0 '
0&
1)
0<
0;
1,
0:
#140000
0$
08
b11 0
b11 .
#145000
1$
18
b10 7
0?
03
0)
#150000
0$
08
#155000
1$
18
b11 7
b0 4
b11 5
#160000
0$
08
#165000
1$
18
b100 6
b0 7
b11 (
1&
1>
1=
1:
#170000
0$
08
#175000
1$
18
b1 7
1?
b1 @
13
b1 1
b0 (
0&
1)
0>
0=
0*
0:
#180000
0$
08
b100 0
b100 .
#185000
1$
18
b10 7
0?
03
0)
#190000
0$
08
#195000
1$
18
b11 7
#200000
0$
08
#205000
1$
18
b100 7
b1 4
b0 5
#210000
0$
08
#215000
1$
18
b0 4
b1 5
b1 '
1&
1<
1:
#220000
0$
08
#225000
1$
18
b11 4
b0 5
1?
b1 A
13
b1 2
b0 '
b1 (
1)
1>
0<
0,
#230000
0$
08
b101 0
b101 .
#235000
1$
18
b0 4
b11 5
b11 @
b11 A
b11 1
b11 2
b11 '
b0 (
0>
1<
1;
1,
1*
#240000
0$
08
b110 0
b110 .
#245000
1$
18
b1 4
b0 5
b1 @
b1 A
b1 1
b1 2
b0 '
b11 (
1>
1=
0<
0;
0,
0*
#250000
0$
08
b111 0
b111 .
#255000
1$
18
b11 @
b11 A
b11 1
b11 2
b1 '
b0 (
0>
0=
1<
1,
1*
#260000
0$
08
b1000 0
b1000 .
#265000
1$
18
b0 4
b1 5
b1 @
b1 A
b1 1
b1 2
0,
0*
#270000
0$
08
b1001 0
b1001 .
#275000
1$
18
b11 4
b0 5
b11 @
b11 A
b11 1
b11 2
b0 '
b1 (
1>
0<
1,
1*
#280000
0$
08
b1010 0
b1010 .
#285000
1$
18
b0 4
b11 5
b1 A
b1 2
b11 '
b0 (
0>
1<
1;
0,
#290000
0$
08
b1011 0
b1011 .
#295000
1$
18
b11 4
b0 5
b1 @
b1 1
b0 '
b11 (
1>
1=
0<
0;
0*
#300000
0$
08
b1100 0
b1100 .
#305000
1$
18
b0 4
b1 5
b11 A
b11 2
b11 '
b0 (
0>
0=
1<
1;
1,
#310000
0$
08
b1101 0
b1101 .
#315000
1$
18
b1 4
b0 5
b1 A
b1 2
b0 '
b1 (
1>
0<
0;
0,
#320000
0$
08
b1110 0
b1110 .
#325000
1$
18
b101 6
b0 7
b11 @
b11 A
b11 1
b11 2
b1 '
b0 (
0>
1<
1,
1*
#330000
0$
08
b1111 0
b1111 .
#335000
1$
18
b1 7
b1 @
b1 A
b1 1
b1 2
b0 '
0&
0<
0,
0*
0:
#340000
0$
08
b10000 0
b10000 .
#345000
1$
18
b10 7
0?
03
0)
#350000
0$
08
#355000
1$
18
b11 7
#360000
0$
08
#365000
1$
18
b100 7
#370000
0$
08
#375000
1$
18
b101 7
#380000
0$
08
#385000
1$
18
b0 4
b11 5
b1 '
1&
1<
1:
#390000
0$
08
#395000
1$
18
b10 6
b0 7
1?
b11 A
13
b11 2
b0 '
b11 (
1)
1>
1=
0<
1,
#400000
0$
08
b10001 0
b10001 .
#405000
1$
18
b1 7
b0 (
0&
0>
0=
0:
#410000
0$
08
b10010 0
b10010 .
#415000
1$
18
b10 7
b11 4
b0 5
0?
03
0)
#420000
0$
08
#425000
1$
18
b1 6
b0 7
b11 '
1&
1<
1;
1:
#430000
0$
08
#435000
1$
18
b1 7
b0 4
b1 5
1?
b1 A
13
b1 2
b0 '
0&
1)
0<
0;
0,
0:
#440000
0$
08
b10011 0
b10011 .
#445000
1$
18
b100 6
b0 7
0?
03
b1 (
1&
0)
1>
1:
#450000
0$
08
#455000
1$
18
b1 7
1?
b11 @
13
b11 1
b0 (
0&
1)
0>
1*
0:
#460000
0$
08
b10100 0
b10100 .
#465000
1$
18
b10 7
0?
03
0)
#470000
0$
08
#475000
1$
18
b11 7
#480000
0$
08
#485000
1$
18
b100 7
